pymodaq_plugins_opencv/__init__.py
pymodaq_plugins_opencv/utils.py
pymodaq_plugins_opencv/daq_move_plugins/__init__.py
pymodaq_plugins_opencv/daq_viewer_plugins/__init__.py
pymodaq_plugins_opencv/daq_viewer_plugins/plugins_0D/__init__.py
pymodaq_plugins_opencv/daq_viewer_plugins/plugins_1D/__init__.py
pymodaq_plugins_opencv/daq_viewer_plugins/plugins_2D/__init__.py
pymodaq_plugins_opencv/daq_viewer_plugins/plugins_2D/daq_2Dviewer_OpenCV.py
pymodaq_plugins_opencv/daq_viewer_plugins/plugins_ND/__init__.py
pymodaq_plugins_opencv/extensions/__init__.py
pymodaq_plugins_opencv/hardware/__init__.py
pymodaq_plugins_opencv/hardware/opencv.py
pymodaq_plugins_opencv/models/__init__.py
pymodaq_plugins_opencv/resources/__init__.py
pymodaq_plugins_opencv/resources/config_template.toml
pymodaq_plugins_opencv-5.0.1.dist-info/METADATA
pymodaq_plugins_opencv-5.0.1.dist-info/WHEEL
pymodaq_plugins_opencv-5.0.1.dist-info/entry_points.txt
pymodaq_plugins_opencv-5.0.1.dist-info/licenses/LICENSE
pymodaq_plugins_opencv-5.0.1.dist-info/RECORD
